{
    "apns": {
        "version": "8",
        "apn": [
            {
                "carrier": "Vodafone Net2",
                "mcc": "268",
                "mnc": "01",
                "apn": "net2.vodafone.pt",
                "proxy": "iproxy.vodafone.pt",
                "port": "80",
                "mmsproxy": "iproxy.vodafone.pt",
                "mmsport": "80",
                "mmsc": "http://mms.vodafone.pt/servlets/mms",
                "user": "vodafone",
                "password": "vodafone",
                "authtype": "3",
                "type": "default,mms"
            },
            {
                "carrier": "Vodafone PT Internet",
                "mcc": "268",
                "mnc": "01",
                "apn": "net2.vodafone.pt",
                "proxy": "iproxy.vodafone.pt",
                "port": "80",
                "mmsc": "http://mms.vodafone.pt/servlets/mms",
                "mmsproxy": "iproxy.vodafone.pt",
                "mmsport": "80",
                "type": "default,supl,mms"
            },
            {
                "carrier": "Vodafone PT WAP MMS",
                "mcc": "268",
                "mnc": "01",
                "apn": "vas.vodafone.pt",
                "user": "vas",
                "password": "vas",
                "mmsc": "http://mms/servlets/mms",
                "mmsproxy": "213.30.27.63",
                "mmsport": "8799",
                "type": "mms"
            },
            {
                "carrier": "Vodafone PT WAP",
                "mcc": "268",
                "mnc": "01",
                "apn": "wap.vodafone.pt",
                "user": "wap",
                "password": "wap",
                "proxy": "172.16.19.50",
                "port": "8799",
                "type": "default,supl"
            },
            {
                "carrier": "Optimus",
                "mcc": "268",
                "mnc": "03",
                "apn": "umts",
                "proxy": "62.169.66.5",
                "port": "8799",
                "mmsproxy": "62.169.66.5",
                "mmsport": "8799",
                "mmsc": "http://mmsc:10021/mmsc",
                "user": "",
                "password": "",
                "authtype": "3",
                "type": "default,mms"
            },
            {
                "carrier": "NOS Internet",
                "mcc": "268",
                "mnc": "03",
                "apn": "umts",
                "type": "default,supl"
            },
            {
                "carrier": "NOS MMS",
                "mcc": "268",
                "mnc": "03",
                "apn": "mms",
                "mmsc": "http://mmsc:10021/mmsc",
                "mmsproxy": "62.169.66.5",
                "mmsport": "8799",
                "type": "mms"
            },
            {
                "carrier": "PT - Optimus Web",
                "mcc": "268",
                "mnc": "03",
                "apn": "umts",
                "proxy": "",
                "port": "",
                "user": "",
                "password": "",
                "mmsc": "",
                "authtype": "1",
                "type": "default,supl"
            },
            {
                "carrier": "PT - Optimus MMS",
                "mcc": "268",
                "mnc": "03",
                "apn": "umts",
                "proxy": "",
                "port": "",
                "user": "",
                "password": "",
                "mmsc": "http://mmsc:10021/mmsc",
                "mmsproxy": "62.169.66.5",
                "mmsport": "8799",
                "authtype": "1",
                "type": "mms"
            },
            {
                "carrier": "Lycamobile PT",
                "mcc": "268",
                "mnc": "04",
                "apn": "data.lycamobile.pt",
                "user": "lmpt",
                "password": "plus",
                "type": "default,supl"
            },
            {
                "carrier": "Lycamobile",
                "mcc": "268",
                "mnc": "04",
                "apn": "data.lycamobile.pt",
                "proxy": "",
                "port": "",
                "user": "lmpt",
                "password": "plus",
                "mmsc": "",
                "mvno_type": "spn",
                "mvno_match_data": "Lycamobile",
                "type": "default,supl"
            },
            {
                "carrier": "MEO Internet",
                "mcc": "268",
                "mnc": "06",
                "apn": "internet",
                "type": "default,supl"
            },
            {
                "carrier": "MEO MMS",
                "mcc": "268",
                "mnc": "06",
                "apn": "mmsc.tmn.pt",
                "user": "tmn",
                "password": "tmnnet",
                "mmsc": "http://mmsc",
                "mmsproxy": "10.111.2.16",
                "mmsport": "8080",
                "type": "mms"
            },
            {
                "carrier": "Vectone Mobile",
                "mcc": "268",
                "mnc": "07",
                "apn": "webpt.mundio.com",
                "proxy": "",
                "port": "",
                "user": "",
                "password": "",
                "mmsc": "",
                "mvno_type": "spn",
                "mvno_match_data": "Vectone Mobile",
                "type": "default,supl"
            }
        ]
    }
}