{
    "apns": {
        "version": "8",
        "apn": [
            {
                "carrier": "Vodafone AL",
                "mcc": "276",
                "mnc": "02",
                "apn": "Twa",
                "type": "default,supl"
            },
            {
                "carrier": "Vodafone AL MMS",
                "mcc": "276",
                "mnc": "02",
                "apn": "vfalmms",
                "mmsc": "http://mmsc.vodafone.al",
                "mmsproxy": "10.0.9.2",
                "mmsport": "8080",
                "type": "mms"
            }
        ]
    }
}